pmxutils/__init__.py
pmxutils/mathtools.py
pmxutils/other.py
pmxutils-0.1.0.dist-info/LICENSE
pmxutils-0.1.0.dist-info/METADATA
pmxutils-0.1.0.dist-info/WHEEL
pmxutils-0.1.0.dist-info/top_level.txt
pmxutils-0.1.0.dist-info/RECORD
