Metadata-Version: 2.1
Name: pmxutils
Version: 0.1.0
Summary: Collection of tools for programmation and modeling X
Home-page: https://github.com/Areskiko/stefan-tools
Author: Stefan Mack
Author-email: stefan_mack@hotmail.com
License: UNKNOWN
Platform: UNKNOWN
Classifier: Programming Language :: Python :: 3
Classifier: License :: OSI Approved :: GNU General Public License v3 (GPLv3)
Classifier: Operating System :: OS Independent
Requires-Python: >=3.7
Requires-Dist: numpy
